<?xml version="1.0" encoding="UTF-8"?>
<symbols xmlns:xi="http://www.w3.org/2001/XInclude">
		<symbol name="Basin General" image_file="../SymbolLibrary/SVG/Fluid/Vessels/BA Basin General.svg" height="104" width="71" x="50" y="50" statesCount="1" >
		<label name="Basin General label" text="Basin General" height="16" width="100" x="171" y="94" />
	</symbol>
		<symbol name="Basin General - second representation" image_file="../SymbolLibrary/SVG/Fluid/Vessels/BA Basin General - second representation.svg" height="104" width="71" x="401" y="50" statesCount="1" >
		<label name="Basin General - second representation label" text="Basin General - second representation" height="16" width="273" x="522" y="94" />
	</symbol>
		<symbol name="Gas Cylinder" image_file="../SymbolLibrary/SVG/Fluid/Vessels/TA Gas Cylinder.svg" height="105" width="71" x="845" y="50" statesCount="1" >
		<label name="Gas Cylinder label" text="Gas Cylinder" height="16" width="90" x="966" y="94" />
	</symbol>
		<symbol name="Tank with floating roof" image_file="../SymbolLibrary/SVG/Fluid/Vessels/TA Tank with floating roof.svg" height="104" width="71" x="50" y="205" statesCount="1" >
		<label name="Tank with floating roof label" text="Tank with floating roof" height="16" width="157" x="171" y="249" />
	</symbol>
		<symbol name="Vessel General" image_file="../SymbolLibrary/SVG/Fluid/Vessels/TA Vessel General.svg" height="104" width="71" x="401" y="205" statesCount="1" >
		<label name="Vessel General label" text="Vessel General" height="16" width="106" x="522" y="249" />
	</symbol>
		<symbol name="Vessel Spherical" image_file="../SymbolLibrary/SVG/Fluid/Vessels/TA Vessel Spherical.svg" height="104" width="71" x="845" y="205" statesCount="1" >
		<label name="Vessel Spherical label" text="Vessel Spherical" height="16" width="116" x="966" y="249" />
	</symbol>
		<symbol name="Vessel with conical heads" image_file="../SymbolLibrary/SVG/Fluid/Vessels/TA Vessel with conical heads.svg" height="104" width="71" x="50" y="359" statesCount="1" >
		<label name="Vessel with conical heads label" text="Vessel with conical heads" height="16" width="180" x="171" y="403" />
	</symbol>
		<symbol name="Vessel with dished heads" image_file="../SymbolLibrary/SVG/Fluid/Vessels/TA Vessel with dished heads.svg" height="104" width="71" x="401" y="359" statesCount="1" >
		<label name="Vessel with dished heads label" text="Vessel with dished heads" height="16" width="176" x="522" y="403" />
	</symbol>
		<symbol name="Vessel with fluidized bed" image_file="../SymbolLibrary/SVG/Fluid/Vessels/TA Vessel with fluidized bed.svg" height="105" width="71" x="845" y="359" statesCount="1" >
		<label name="Vessel with fluidized bed label" text="Vessel with fluidized bed" height="16" width="173" x="966" y="403" />
	</symbol>
	</symbols>