<?xml version="1.0" encoding="UTF-8"?>
<symbols xmlns:xi="http://www.w3.org/2001/XInclude">
		<symbol name="Basin General" image_file="../SymbolLibrary/SVG/Fluid/Vessels/BA Basin General.svg" height="181" width="124" x="100" y="101" statesCount="1" >
		<label name="Basin General label" text="Basin General" height="33" width="197" x="324" y="175" />
	</symbol>
		<symbol name="Basin General - second representation" image_file="../SymbolLibrary/SVG/Fluid/Vessels/BA Basin General - second representation.svg" height="181" width="124" x="783" y="101" statesCount="1" >
		<label name="Basin General - second representation label" text="Basin General - second representation" height="33" width="540" x="1007" y="175" />
	</symbol>
		<symbol name="Gas Cylinder" image_file="../SymbolLibrary/SVG/Fluid/Vessels/TA Gas Cylinder.svg" height="184" width="124" x="1647" y="100" statesCount="1" >
		<label name="Gas Cylinder label" text="Gas Cylinder" height="33" width="181" x="1871" y="176" />
	</symbol>
		<symbol name="Tank with floating roof" image_file="../SymbolLibrary/SVG/Fluid/Vessels/TA Tank with floating roof.svg" height="181" width="124" x="100" y="384" statesCount="1" >
		<label name="Tank with floating roof label" text="Tank with floating roof" height="33" width="312" x="324" y="458" />
	</symbol>
		<symbol name="Vessel General" image_file="../SymbolLibrary/SVG/Fluid/Vessels/TA Vessel General.svg" height="181" width="124" x="783" y="384" statesCount="1" >
		<label name="Vessel General label" text="Vessel General" height="33" width="209" x="1007" y="458" />
	</symbol>
		<symbol name="Vessel Spherical" image_file="../SymbolLibrary/SVG/Fluid/Vessels/TA Vessel Spherical.svg" height="181" width="124" x="1647" y="384" statesCount="1" >
		<label name="Vessel Spherical label" text="Vessel Spherical" height="33" width="229" x="1871" y="458" />
	</symbol>
		<symbol name="Vessel with conical heads" image_file="../SymbolLibrary/SVG/Fluid/Vessels/TA Vessel with conical heads.svg" height="181" width="124" x="100" y="666" statesCount="1" >
		<label name="Vessel with conical heads label" text="Vessel with conical heads" height="33" width="359" x="324" y="740" />
	</symbol>
		<symbol name="Vessel with dished heads" image_file="../SymbolLibrary/SVG/Fluid/Vessels/TA Vessel with dished heads.svg" height="181" width="124" x="783" y="666" statesCount="1" >
		<label name="Vessel with dished heads label" text="Vessel with dished heads" height="33" width="355" x="1007" y="740" />
	</symbol>
		<symbol name="Vessel with fluidized bed" image_file="../SymbolLibrary/SVG/Fluid/Vessels/TA Vessel with fluidized bed.svg" height="184" width="124" x="1647" y="665" statesCount="1" >
		<label name="Vessel with fluidized bed label" text="Vessel with fluidized bed" height="33" width="349" x="1871" y="741" />
	</symbol>
	</symbols>